{
    "sizes": [
        {
            "index": 0,
            "size": 587
        },
        {
            "index": 1,
            "size": 239
        },
        {
            "index": 2,
            "size": 340
        },
        {
            "index": 3,
            "size": 3392
        },
        {
            "index": 4,
            "size": 285
        },
        {
            "index": 5,
            "size": 395
        },
        {
            "index": 6,
            "size": 615
        },
        {
            "index": 7,
            "size": 543
        },
        {
            "index": 8,
            "size": 372
        },
        {
            "index": 9,
            "size": 609
        },
        {
            "index": 10,
            "size": 1229
        },
        {
            "index": 11,
            "size": 574
        },
        {
            "index": 12,
            "size": 316
        },
        {
            "index": 13,
            "size": 0
        },
        {
            "index": 14,
            "size": 0
        }
    ]
}