{
    "sizes": [
        {
            "index": 0,
            "size": 477
        },
        {
            "index": 1,
            "size": 1880
        },
        {
            "index": 2,
            "size": 142
        },
        {
            "index": 3,
            "size": 399
        },
        {
            "index": 4,
            "size": 93
        },
        {
            "index": 5,
            "size": 206
        },
        {
            "index": 6,
            "size": 149
        },
        {
            "index": 7,
            "size": 242
        },
        {
            "index": 8,
            "size": 108
        },
        {
            "index": 9,
            "size": 207
        },
        {
            "index": 10,
            "size": 79
        },
        {
            "index": 11,
            "size": 134
        },
        {
            "index": 12,
            "size": 271
        },
        {
            "index": 13,
            "size": 320
        },
        {
            "index": 14,
            "size": 197
        }
    ]
}