{
    "sizes": [
        {
            "index": 0,
            "size": 521
        },
        {
            "index": 1,
            "size": 160
        },
        {
            "index": 2,
            "size": 22
        },
        {
            "index": 3,
            "size": 6
        },
        {
            "index": 4,
            "size": 26
        },
        {
            "index": 5,
            "size": 62
        },
        {
            "index": 6,
            "size": 1925
        },
        {
            "index": 7,
            "size": 1226
        },
        {
            "index": 8,
            "size": 105
        },
        {
            "index": 9,
            "size": 466
        },
        {
            "index": 10,
            "size": 139
        },
        {
            "index": 11,
            "size": 88
        },
        {
            "index": 12,
            "size": 31
        }
    ]
}